Workbook

Sheet Export Summary
B3: This document was exported from Numbers. Each table was converted to an Excel worksheet. All other objects on each Numbers sheet were placed on separate worksheets. Please be aware that formula calculations may differ in Excel.
B7: Numbers Sheet Name | C7: Numbers Table Name | D7: Excel Worksheet Name
B9: Retail Sales Dataset
C10: Retail Sales Dataset | D10: Retail Sales Dataset - Retail S
B11: dashboard
C12: Retail Sales Dashboard | D12: dashboard - Retail Sales Dashbo

Sheet Retail Sales Dataset - Retail S
A1: Retail Sales Dataset
A2: Month | B2: Region | C2: Product | D2: Units Sold | E2: Unit Price | F2: Sales | G2: Profit | H2: Profit Margin
A3: 46023 | B3: North | C3: Laptop | D3: 18 | E3: 720 | F3: 12960 | G3: 2332.8 | H3: 0.18
A4: 46023 | B4: South | C4: Phone | D4: 42 | E4: 390 | F4: 16380 | G4: 2293.2 | H4: 0.14
A5: 46023 | B5: East | C5: Tablet | D5: 25 | E5: 260 | F5: 6500 | G5: 1040 | H5: 0.16
A6: 46023 | B6: West | C6: Monitor | D6: 30 | E6: 210 | F6: 6300 | G6: 756 | H6: 0.12
A7: 46054 | B7: North | C7: Phone | D7: 35 | E7: 390 | F7: 13650 | G7: 1911 | H7: 0.14
A8: 46054 | B8: South | C8: Laptop | D8: 15 | E8: 720 | F8: 10800 | G8: 1944 | H8: 0.18
A9: 46054 | B9: East | C9: Monitor | D9: 28 | E9: 210 | F9: 5880 | G9: 705.6 | H9: 0.12
A10: 46054 | B10: West | C10: Tablet | D10: 32 | E10: 260 | F10: 8320 | G10: 1331.2 | H10: 0.16
A11: 46082 | B11: North | C11: Tablet | D11: 30 | E11: 260 | F11: 7800 | G11: 1248 | H11: 0.16
A12: 46082 | B12: South | C12: Monitor | D12: 36 | E12: 210 | F12: 7560 | G12: 907.2 | H12: 0.12
A13: 46082 | B13: East | C13: Laptop | D13: 20 | E13: 720 | F13: 14400 | G13: 2592 | H13: 0.18
A14: 46082 | B14: West | C14: Phone | D14: 48 | E14: 390 | F14: 18720 | G14: 2620.8 | H14: 0.14
... A50: 46357 | B50: West | C50: Laptop | D50: 26 | E50: 720 | F50: 18720 | G50: 3369.6 | H50: 0.18

Sheet dashboard - Retail Sales Dashbo
A1: Retail Sales Dashboard
A2: VEDA TECHNOLOGY SALES PERFORMANCE DASHBOARD
A5: Month | B5: 46054 | D5: Region | E5: All Regions
A7: TOTAL SALES | C7: TOTAL PROFIT | E7: UNIT SOLD | G7: PROFIT MARGIN
A8: {=_xlfn.SUMIFS('Retail Sales Dataset - Retail S'!F2:F50,'Retail Sales Dataset - Retail S'!A2:A50,IF(B5="All Months","<>",B5),'Retail Sales Dataset - Retail S'!B2:B50,IF(E5="All Regions","<>",E5))} -> 38650 | C8: {=_xlfn.SUMIFS('Retail Sales Dataset - Retail S'!G2:G50,'Retail Sales Dataset - Retail S'!A2:A50,IF(B5="All Months","<>",B5),'Retail Sales Dataset - Retail S'!B2:B50,IF(E5="All Regions","<>",E5))} -> 5891.8 | E8: {=_xlfn.SUMIFS('Retail Sales Dataset - Retail S'!D2:D50,'Retail Sales Dataset - Retail S'!A2:A50,IF(B5="All Months","<>",B5),'Retail Sales Dataset - Retail S'!B2:B50,IF(E5="All Regions","<>",E5))} -> 110 | G8: {=_xlfn.IFERROR(C8/A8,0)} -> 0.15243984
A12: MONTHLY SALES SUMMARY | E12: REGIONAL SALES SUMMARY
A13: Month | B13: Sales | C13: Growth % | E13: Regions | F13: Sales
A14: 46023 | B14: {=SUMIF('Retail Sales Dataset - Retail S'!A2:A50,A14,'Retail Sales Dataset - Retail S'!F2:F50)} -> 42140 | E14: North | F14: {=SUMIF('Retail Sales Dataset - Retail S'!B2:B50,E14,'Retail Sales Dataset - Retail S'!F2:F50)} -> 144070
A15: 46054 | B15: {=SUMIF('Retail Sales Dataset - Retail S'!A2:A50,A15,'Retail Sales Dataset - Retail S'!F2:F50)} -> 38650 | C15: {=_xlfn.IFERROR((B15-B14)/B14,0)} -> -0.082819174 | E15: South | F15: {=SUMIF('Retail Sales Dataset - Retail S'!B2:B50,E15,'Retail Sales Dataset - Retail S'!F2:F50)} -> 146270
A16: 46082 | B16: {=SUMIF('Retail Sales Dataset - Retail S'!A2:A50,A16,'Retail Sales Dataset - Retail S'!F2:F50)} -> 48480 | C16: {=_xlfn.IFERROR((B16-B15)/B15,0)} -> 0.25433376 | E16: East | F16: {=SUMIF('Retail Sales Dataset - Retail S'!B2:B50,E16,'Retail Sales Dataset - Retail S'!F2:F50)} -> 149870
A17: 46113 | B17: {=SUMIF('Retail Sales Dataset - Retail S'!A2:A50,A17,'Retail Sales Dataset - Retail S'!F2:F50)} -> 44210 | C17: {=_xlfn.IFERROR((B17-B16)/B16,0)} -> -0.088077558 | E17: West | F17: {=SUMIF('Retail Sales Dataset - Retail S'!B2:B50,E17,'Retail Sales Dataset - Retail S'!F2:F50)} -> 156090
A18: 46143 | B18: {=SUMIF('Retail Sales Dataset - Retail S'!A2:A50,A18,'Retail Sales Dataset - Retail S'!F2:F50)} -> 49920 | C18: {=_xlfn.IFERROR((B18-B17)/B17,0)} -> 0.1291563
A19: 46174 | B19: {=SUMIF('Retail Sales Dataset - Retail S'!A2:A50,A19,'Retail Sales Dataset - Retail S'!F2:F50)} -> 46450 | C19: {=_xlfn.IFERROR((B19-B18)/B18,0)} -> -0.069511218
A20: 46204 | B20: {=SUMIF('Retail Sales Dataset - Retail S'!A2:A50,A20,'Retail Sales Dataset - Retail S'!F2:F50)} -> 54260 | C20: {=_xlfn.IFERROR((B20-B19)/B19,0)} -> 0.16813778
A21: 46235 | B21: {=SUMIF('Retail Sales Dataset - Retail S'!A2:A50,A21,'Retail Sales Dataset - Retail S'!F2:F50)} -> 50780 | C21: {=_xlfn.IFERROR((B21-B20)/B20,0)} -> -0.064135643
A22: 46266 | B22: {=SUMIF('Retail Sales Dataset - Retail S'!A2:A50,A22,'Retail Sales Dataset - Retail S'!F2:F50)} -> 55050 | C22: {=_xlfn.IFERROR((B22-B21)/B21,0)} -> 0.084088224
A23: 46296 | B23: {=SUMIF('Retail Sales Dataset - Retail S'!A2:A50,A23,'Retail Sales Dataset - Retail S'!F2:F50)} -> 51190 | C23: {=_xlfn.IFERROR((B23-B22)/B22,0)} -> -0.070118074
A24: 46327 | B24: {=SUMIF('Retail Sales Dataset - Retail S'!A2:A50,A24,'Retail Sales Dataset - Retail S'!F2:F50)} -> 58670 | C24: {=_xlfn.IFERROR((B24-B23)/B23,0)} -> 0.14612229
A25: 46357 | B25: {=SUMIF('Retail Sales Dataset - Retail S'!A2:A50,A25,'Retail Sales Dataset - Retail S'!F2:F50)} -> 56500 | C25: {=_xlfn.IFERROR((B25-B24)/B24,0)} -> -0.036986535
A28: PRODUCT SALES SUMMARY
A29: Product | B29: Unit Sold | C29: Total Sales
A30: Laptop | B30: {=SUMIF('Retail Sales Dataset - Retail S'!C2:C50,A30,'Retail Sales Dataset - Retail S'!D2:D50)} -> 252 | C30: {=SUMIF('Retail Sales Dataset - Retail S'!C2:C50,A30,'Retail Sales Dataset - Retail S'!F2:F50)} -> 181440
A31: Phone | B31: {=SUMIF('Retail Sales Dataset - Retail S'!C2:C50,A31,'Retail Sales Dataset - Retail S'!D2:D50)} -> 576 | C31: {=SUMIF('Retail Sales Dataset - Retail S'!C2:C50,A31,'Retail Sales Dataset - Retail S'!F2:F50)} -> 224640
A32: Tablet | B32: {=SUMIF('Retail Sales Dataset - Retail S'!C2:C50,A32,'Retail Sales Dataset - Retail S'!D2:D50)} -> 394 | C32: {=SUMIF('Retail Sales Dataset - Retail S'!C2:C50,A32,'Retail Sales Dataset - Retail S'!F2:F50)} -> 102440
A33: Monitor | B33: {=SUMIF('Retail Sales Dataset - Retail S'!C2:C50,A33,'Retail Sales Dataset - Retail S'!D2:D50)} -> 418 | C33: {=SUMIF('Retail Sales Dataset - Retail S'!C2:C50,A33,'Retail Sales Dataset - Retail S'!F2:F50)} -> 87780
